Aboutn/__init__.py
Aboutn/quadrado.py
Aboutn/quadro.py
Aboutn/tela.py
Aboutn-0.2.2.10.dist-info/LICENSE
Aboutn-0.2.2.10.dist-info/METADATA
Aboutn-0.2.2.10.dist-info/WHEEL
Aboutn-0.2.2.10.dist-info/top_level.txt
Aboutn-0.2.2.10.dist-info/RECORD
